neverlib/__init__.py
neverlib/Docs/audio_aug/test_volume.ipynb
neverlib/Docs/audio_aug_test/test_snr.py
neverlib/Docs/audio_aug_test/test_volume.ipynb
neverlib/Docs/audio_aug_test/test_volume.py
neverlib/Docs/filter/biquad.ipynb
neverlib/Docs/filter/filter_family.ipynb
neverlib/Docs/filter/highpass.ipynb
neverlib/Docs/filter/scipy_filter_family.ipynb
neverlib/Docs/vad/VAD_Energy.ipynb
neverlib/Docs/vad/VAD_Silero.ipynb
neverlib/Docs/vad/VAD_WebRTC.ipynb
neverlib/Docs/vad/VAD_funasr.ipynb
neverlib/Docs/vad/VAD_rvADfast.ipynb
neverlib/Docs/vad/VAD_statistics.ipynb
neverlib/Docs/vad/VAD_tenVAD.ipynb
neverlib/Docs/vad/VAD_vadlib.ipynb
neverlib/Docs/vad/VAD_whisper.ipynb
neverlib/QA/ImpactNoiseRejection.py
neverlib/QA/gen_init.py
neverlib/QA/get_fun.py
neverlib/QA/html2markdown.py
neverlib/QA/impact_noise_rejection.png
neverlib/QA/out.pcm
neverlib/QA/out.wav
neverlib/audio_aug/HarmonicDistortion.py
neverlib/audio_aug/README.md
neverlib/audio_aug/TFDrop.py
neverlib/audio_aug/TFMask.py
neverlib/audio_aug/__init__.py
neverlib/audio_aug/audio_aug.py
neverlib/audio_aug/clip_aug.py
neverlib/audio_aug/coder_aug.py
neverlib/audio_aug/coder_aug2.py
neverlib/audio_aug/loss_packet_aug.py
neverlib/audio_aug/quant_aug.py
neverlib/data/000_short_enhance.wav
neverlib/data/3956_speech.wav
neverlib/data/3956_sweep.wav
neverlib/data/vad_example.wav
neverlib/data/white.wav
neverlib/data/white_EQ.wav
neverlib/data/white_matched.wav
neverlib/data_analyze/README.md
neverlib/data_analyze/__init__.py
neverlib/data_analyze/dataset_analyzer.py
neverlib/data_analyze/quality_metrics.py
neverlib/data_analyze/rms_distrubution.py
neverlib/data_analyze/spectral_analysis.py
neverlib/data_analyze/statistics.py
neverlib/data_analyze/temporal_features.py
neverlib/data_analyze/visualization.py
neverlib/filter/README.md
neverlib/filter/__init__.py
neverlib/filter/biquad.py
neverlib/filter/common.py
neverlib/filter/core.py
neverlib/filter/auto_eq/README.md
neverlib/filter/auto_eq/__init__.py
neverlib-0.2.9.dist-info/licenses/LICENSE
neverlib-0.2.9.dist-info/METADATA
neverlib-0.2.9.dist-info/WHEEL
neverlib-0.2.9.dist-info/top_level.txt
neverlib-0.2.9.dist-info/RECORD
