Metadata-Version: 2.4
Name: neverlib
Version: 0.2.9
Summary: A successful sign for python setup
Author-email: "Never.Ling" <1786088386@qq.com>
License: MIT
Project-URL: Homepage, https://www.cnblogs.com/LXP-Never
Project-URL: Bug Tracker, https://github.com/yourusername/neverlib/issues
Project-URL: Documentation, https://github.com/yourusername/neverlib
Project-URL: Source Code, https://github.com/yourusername/neverlib
Classifier: Programming Language :: Python :: 3
Classifier: Programming Language :: Python :: 3.11
Classifier: Programming Language :: Python :: 3.12
Classifier: Programming Language :: Python :: 3.13
Classifier: License :: OSI Approved :: MIT License
Classifier: Operating System :: OS Independent
Requires-Python: >=3.6
License-File: LICENSE
Requires-Dist: lazy-loader>=0.4
Provides-Extra: analysis
Requires-Dist: numpy; extra == "analysis"
Requires-Dist: scipy; extra == "analysis"
Requires-Dist: tqdm; extra == "analysis"
Requires-Dist: joblib; extra == "analysis"
Requires-Dist: noisereduce; extra == "analysis"
Provides-Extra: io
Requires-Dist: soundfile; extra == "io"
Requires-Dist: pydub; extra == "io"
Provides-Extra: plot
Requires-Dist: matplotlib; extra == "plot"
Provides-Extra: vad
Requires-Dist: torch; extra == "vad"
Requires-Dist: torchaudio; extra == "vad"
Requires-Dist: librosa; extra == "vad"
Requires-Dist: webrtcvad; extra == "vad"
Requires-Dist: funasr; extra == "vad"
Requires-Dist: openai-whisper; extra == "vad"
Requires-Dist: transformers; extra == "vad"
Provides-Extra: gpu
Requires-Dist: GPUtil; extra == "gpu"
Provides-Extra: all
Requires-Dist: neverlib[analysis]; extra == "all"
Requires-Dist: neverlib[io]; extra == "all"
Requires-Dist: neverlib[plot]; extra == "all"
Requires-Dist: neverlib[vad]; extra == "all"
Requires-Dist: neverlib[gpu]; extra == "all"
Dynamic: license-file
